<?xml version="1.0" encoding="UTF-8"?>
<LanguageData>
	
	<QualityBuilder>QualityBuilder</QualityBuilder>
	<QualityBuilderCommand.Label>Якість будівлі</QualityBuilderCommand.Label>

	<QualityBuilderOn.Label>ПОМИЛКА</QualityBuilderOn.Label>
	<QualityBuilderOn.Desc>ЛКМ - встановити вимогу якості. ПКМ - обрати якість.</QualityBuilderOn.Desc>
	<QualityBuilder.Already>ПОМИЛКА</QualityBuilder.Already>

	<QualityBuilderOff.Label>ПОМИЛКА</QualityBuilderOff.Label>
	<QualityBuilderOff.Desc>Обрана якість: {0}. ЛКМ - вняти вимогу якості. ПКМ - обрати якість.</QualityBuilderOff.Desc>
	<QualityBuilder.Nothing>ПОМИЛКА</QualityBuilder.Nothing>

	<QualityBuilder.SelectedSettings>Налаштування</QualityBuilder.SelectedSettings>
	<QualityBuilder.CurrentMap>Поточна мапа</QualityBuilder.CurrentMap>
	<QualityBuilder.Global>Налаштування за замовчуванням</QualityBuilder.Global>
	<QualityBuilder.EnableByDefault>Увімкнути QualityBuilder за замовчуванням</QualityBuilder.EnableByDefault>
	<QualityBuilder.IgnoreAtSkill>Ігнорувати QualityBuilder на рівні будівництва {0}</QualityBuilder.IgnoreAtSkill>
	<QualityBuilder.MinQuality>Мінімальна якість за замовчуванням</QualityBuilder.MinQuality>
	<QualityBuilder.OverrideBestBuilder>Override best builder with</QualityBuilder.OverrideBestBuilder>
</LanguageData>
